chigpy/__init__.py
chigpy-0.0.42.dist-info/LICENSE
chigpy-0.0.42.dist-info/METADATA
chigpy-0.0.42.dist-info/WHEEL
chigpy-0.0.42.dist-info/top_level.txt
chigpy-0.0.42.dist-info/RECORD
