Metadata-Version: 2.1
Name: chigpy
Version: 0.0.42
Summary: A python package built by Chirag Aswani
Home-page: https://github.com/ChiragAswani/chigpy
Author: Chirag Aswani
Author-email: chirag@aswani.net
License: UNKNOWN
Platform: UNKNOWN
Classifier: Programming Language :: Python :: 3
Classifier: License :: OSI Approved :: MIT License
Classifier: Operating System :: OS Independent
